gsnodegraph/__init__.py
gsnodegraph/constants.py
gsnodegraph/assets/__init__.py
gsnodegraph/assets/bitmaps.py
gsnodegraph/graph/__init__.py
gsnodegraph/graph/base.py
gsnodegraph/graph/btn.py
gsnodegraph/graph/utils/__init__.py
gsnodegraph/graph/utils/z_matrix.py
gsnodegraph/node/__init__.py
gsnodegraph/node/node.py
gsnodegraph/node/socket.py
gsnodegraph/node/utils.py
gsnodegraph/node/wire.py
gsnodegraph-0.5.6.dist-info/LICENSE
gsnodegraph-0.5.6.dist-info/METADATA
gsnodegraph-0.5.6.dist-info/WHEEL
gsnodegraph-0.5.6.dist-info/top_level.txt
gsnodegraph-0.5.6.dist-info/RECORD
